{
  "generated_at": "2026-07-01T08:52:19Z",
  "data": {
    "ES": {
      "2026-07-01": [
        {
          "home": "México",
          "away": "Ecuador",
          "channels": [
            "BarTV Mundial (M300)"
          ],
          "time": "04:00"
        },
        {
          "home": "Inglaterra",
          "away": "R.D. Congo",
          "channels": [
            "La 2 Cat",
            "La 1 TVE"
          ],
          "time": "18:00"
        },
        {
          "home": "España",
          "away": "Islandia",
          "channels": [
            "Teledeporte",
            "RTVE Play"
          ],
          "time": "17:00"
        },
        {
          "home": "FK Tukums 2000",
          "away": "SK Super Nova",
          "channels": [
            "OneFootball PPV"
          ],
          "time": "17:00"
        }
      ]
    },
    "PT": {
      "2026-07-01": [
        {
          "home": "França",
          "away": "Suécia Mundial FIFA, 3 a 0",
          "channels": [
            "Sport.Tv1",
            "Vídeo"
          ],
          "time": "00:00"
        },
        {
          "home": "México",
          "away": "Equador Mundial FIFA, 2 a 0",
          "channels": [
            "Sport.Tv5",
            "Vídeo"
          ],
          "time": "02:00"
        },
        {
          "home": "Inglaterra",
          "away": "R. Congo Mundial FIFA, 1/16 F",
          "channels": [
            "Sport.Tv5",
            "Betano"
          ],
          "time": "17:00"
        },
        {
          "home": "Bélgica",
          "away": "Senegal Mundial FIFA, 1/16 F",
          "channels": [
            "RTP 1",
            "Sport.Tv5",
            "LiveModeTv",
            "Betano"
          ],
          "time": "21:00"
        },
        {
          "home": "Estados Unidos",
          "away": "Bósnia H. Mundial FIFA, 1/16 F",
          "channels": [
            "Sport.Tv5",
            "Betano"
          ],
          "time": "01:00"
        },
        {
          "home": "Espanha",
          "away": "Áustria Mundial FIFA, 1/16 F",
          "channels": [
            "Sport.Tv5"
          ],
          "time": "20:00"
        },
        {
          "home": "Liga Portugal Awards",
          "away": "e Sorteios",
          "channels": [
            "Sport.Tv+",
            "Liga Tv"
          ],
          "time": "21:00"
        },
        {
          "home": "Portugal",
          "away": "Croácia Mundial FIFA, 1/16 F",
          "channels": [
            "SIC",
            "Sport.Tv5",
            "LiveModeTv"
          ],
          "time": "00:00"
        },
        {
          "home": "Suíça",
          "away": "Argélia Mundial FIFA, 1/16 F",
          "channels": [
            "Sport.Tv5"
          ],
          "time": "04:00"
        },
        {
          "home": "Austrália",
          "away": "Egito Mundial FIFA, 1/16 F",
          "channels": [
            "Sport.Tv5"
          ],
          "time": "19:00"
        },
        {
          "home": "Argentina",
          "away": "Cabo Verde Mundial FIFA, 1/16 F",
          "channels": [
            "TVI",
            "Sport.Tv1",
            "LiveModeTv"
          ],
          "time": "23:00"
        },
        {
          "home": "Colômbia",
          "away": "Gana Mundial FIFA, 1/16 F",
          "channels": [
            "Sport.Tv5"
          ],
          "time": "02:30"
        },
        {
          "home": "Canadá",
          "away": "Marrocos Mundial FIFA 2026, 1/8 F",
          "channels": [
            "Sport.Tv5"
          ],
          "time": "18:00"
        },
        {
          "home": "Brasil",
          "away": "Noruega Mundial FIFA 2026, 1/8 F",
          "channels": [
            "Sport.Tv5"
          ],
          "time": "21:00"
        },
        {
          "home": "Vários",
          "away": "Jogos Mundial FIFA 2026, 1/4 F",
          "channels": [
            "Sport.Tv5"
          ],
          "time": "21:00"
        },
        {
          "home": "Vários",
          "away": "Jogos Mundial FIFA 2026, MF",
          "channels": [
            "Sport.Tv5"
          ],
          "time": "20:00"
        },
        {
          "home": "Jogo",
          "away": "FINAL Mundial FIFA 2026",
          "channels": [
            "Sport.Tv5"
          ],
          "time": "20:00"
        },
        {
          "home": "Portugal",
          "away": "País Gales Liga Nações 2026/27",
          "channels": [
            "RTP 1"
          ],
          "time": "19:45"
        },
        {
          "home": "Portugal",
          "away": "Noruega Liga Nações 2026/27",
          "channels": [
            "RTP 1"
          ],
          "time": "19:45"
        }
      ]
    },
    "IT": {
      "2026-07-01": [
        {
          "home": "Olanda-Marocco (Mondiali)",
          "away": "",
          "channels": [
            "DAZN"
          ],
          "time": "03:00"
        },
        {
          "home": "Costa d’Avorio-Norvegia (Mondiali)",
          "away": "",
          "channels": [
            "DAZN"
          ],
          "time": "19:00"
        },
        {
          "home": "Francia-Svezia (Mondiali)",
          "away": "",
          "channels": [
            "DAZN"
          ],
          "time": "23:00"
        },
        {
          "home": "Messico-Ecuador (Mondiali)",
          "away": "",
          "channels": [
            "DAZN"
          ],
          "time": "03:00"
        },
        {
          "home": "Inghilterra-RD Congo (Mondiali)",
          "away": "",
          "channels": [
            "DAZN"
          ],
          "time": "18:00"
        },
        {
          "home": "Belgio-Senegal (Mondiali)",
          "away": "",
          "channels": [
            "DAZN"
          ],
          "time": "22:00"
        },
        {
          "home": "Stati Uniti-Bosnia (Mondiali)",
          "away": "",
          "channels": [
            "DAZN"
          ],
          "time": "02:00"
        },
        {
          "home": "Croazia-Italia (Europei Under 19)",
          "away": "",
          "channels": [
            "RAI SPORT"
          ],
          "time": "15:00"
        },
        {
          "home": "Spagna-Austria (Mondiali)",
          "away": "",
          "channels": [
            "DAZN"
          ],
          "time": "21:00"
        },
        {
          "home": "Portogallo-Croazia (Mondiali)",
          "away": "",
          "channels": [
            "DAZN"
          ],
          "time": "01:00"
        },
        {
          "home": "Svizzera-Algeria (Mondiali)",
          "away": "",
          "channels": [
            "DAZN"
          ],
          "time": "05:00"
        },
        {
          "home": "Australia-Egitto (Mondiali)",
          "away": "",
          "channels": [
            "DAZN"
          ],
          "time": "20:00"
        }
      ]
    },
    "US": {
      "2026-07-01": [
        {
          "home": "Mexico",
          "away": "Ecuador(FIFA World Cup)",
          "channels": [
            "FOX",
            "Telemundo",
            "Fubo",
            "DirecTV Stream",
            "Sling Blue",
            "Hulu + Live TV",
            "Peacock Premium"
          ],
          "time": ""
        },
        {
          "home": "DR Congo",
          "away": "England(FIFA World Cup)",
          "channels": [
            "FOX",
            "Telemundo",
            "Fubo",
            "DirecTV Stream",
            "Sling Blue",
            "Hulu + Live TV",
            "Peacock Premium"
          ],
          "time": ""
        },
        {
          "home": "Belgium",
          "away": "Senegal(FIFA World Cup)",
          "channels": [
            "FS1",
            "Telemundo",
            "Fubo",
            "DirecTV Stream",
            "Sling Blue",
            "Hulu + Live TV",
            "Peacock Premium"
          ],
          "time": ""
        },
        {
          "home": "Charlotte Independence",
          "away": "Corpus Christi FC(USL League One)",
          "channels": [
            "ESPN+"
          ],
          "time": ""
        },
        {
          "home": "Chattanooga Red Wolves",
          "away": "Westchester SC(USL League One)",
          "channels": [
            "ESPN+"
          ],
          "time": ""
        },
        {
          "home": "United States",
          "away": "Bosnia and Herzegovina(FIFA World Cup)",
          "channels": [
            "FOX",
            "Telemundo",
            "Fubo",
            "DirecTV Stream",
            "Sling Blue",
            "Hulu + Live TV",
            "Peacock Premium"
          ],
          "time": ""
        },
        {
          "home": "Union Omaha",
          "away": "AV Alta FC(USL League One)",
          "channels": [
            "ESPN+"
          ],
          "time": ""
        },
        {
          "home": "Spokane Velocity FC",
          "away": "Forward Madison FC(USL League One)",
          "channels": [
            "CBS Sports Network",
            "Fubo",
            "DirecTV Stream",
            "Hulu + Live TV"
          ],
          "time": ""
        },
        {
          "home": "Spain",
          "away": "Austria(FIFA World Cup)",
          "channels": [
            "FOX",
            "Telemundo",
            "Fubo",
            "DirecTV Stream",
            "Sling Blue",
            "Hulu + Live TV",
            "Peacock Premium"
          ],
          "time": ""
        },
        {
          "home": "Portugal",
          "away": "Croatia(FIFA World Cup)",
          "channels": [
            "FOX",
            "Telemundo",
            "Fubo",
            "DirecTV Stream",
            "Sling Blue",
            "Hulu + Live TV",
            "Peacock Premium"
          ],
          "time": ""
        },
        {
          "home": "STREAMING OFFERS",
          "away": "",
          "channels": [
            "Sign Up",
            "Browse Offers"
          ],
          "time": ""
        }
      ]
    }
  }
}